LICENSE
MANIFEST.in
README.md
requirements.txt
setup.py
perovskite/__init__.py
perovskite.egg-info/PKG-INFO
perovskite.egg-info/SOURCES.txt
perovskite.egg-info/dependency_links.txt
perovskite.egg-info/requires.txt
perovskite.egg-info/top_level.txt
perovskite/calculation_filter/__init__.py
perovskite/calculation_filter/filter_dup.py
perovskite/calculation_filter/filter_stability.py
perovskite/core/__init__.py
perovskite/core/base.py
perovskite/core/general_rotate.py
perovskite/core/general_standard.py
perovskite/core/general_substitute.py
perovskite/core/rotate_substitude.py
perovskite/data/__init__.py
perovskite/data/generate.py
perovskite/data/small_molecule_ion_data.py
perovskite/extra/__init__.py
perovskite/extra/hpc2ml/__init__.py
perovskite/extra/hpc2ml/data/__init__.py
perovskite/extra/hpc2ml/data/batchdata.py
perovskite/extra/hpc2ml/data/dataset.py
perovskite/extra/hpc2ml/data/structuretodata.py
perovskite/extra/hpc2ml/data/embedding/__init__.py
perovskite/extra/hpc2ml/data/embedding/cohesive_energy.py
perovskite/extra/hpc2ml/data/embedding/continuous_embeddings.py
perovskite/extra/hpc2ml/data/io/__init__.py
perovskite/extra/hpc2ml/data/io/ase.py
perovskite/extra/hpc2ml/data/io/asedb.py
perovskite/extra/hpc2ml/data/io/main.py
perovskite/extra/hpc2ml/data/io/pmgjson.py
perovskite/extra/hpc2ml/data/io/table.py
perovskite/extra/hpc2ml/data/io/vasp.py
perovskite/extra/hpc2ml/data/nequlip_support/AtomicDataDict.py
perovskite/extra/hpc2ml/data/nequlip_support/__init__.py
perovskite/extra/hpc2ml/data/nequlip_support/_irrreps_support.py
perovskite/extra/hpc2ml/data/nequlip_support/_keys.py
perovskite/extra/hpc2ml/data/nequlip_support/_transforms.py
perovskite/extra/hpc2ml/data/nequlip_support/fields.py
perovskite/extra/hpc2ml/data/nequlip_support/typing.py
perovskite/extra/hpc2ml/data/preprocessing/__init__.py
perovskite/extra/hpc2ml/data/preprocessing/pack.py
perovskite/extra/hpc2ml/data/preprocessing/structure_matcher.py
perovskite/extra/hpc2ml/data/sampler/__init__.py
perovskite/extra/hpc2ml/data/sampler/random_group_sampler.py
perovskite/extra/hpc2ml/db/__init__.py
perovskite/extra/hpc2ml/db/ase_db_extension/__init__.py
