Metadata-Version: 2.1
Name: perovskite
Version: 0.0.3
Summary: This is one tool to generator perovskite structures for calculation, such as First-principles calculations.
Home-page: https://github.com/boliqq07/perovskite
Author: wangchangxin
Author-email: 986798607@qq.com
Maintainer: wangchangxin
Keywords: perovskite, structure
Platform: Windows
Platform: Unix
Classifier: Development Status :: 4 - Beta
Classifier: Intended Audience :: Science/Research
Classifier: Natural Language :: English
Classifier: Operating System :: Microsoft :: Windows
Classifier: Operating System :: Unix
Classifier: Programming Language :: Python :: 3.6
Classifier: Programming Language :: Python :: 3.7
Classifier: Programming Language :: Python :: 3.8
Classifier: Programming Language :: Python :: 3.9
Classifier: Programming Language :: Python :: 3.10
Requires-Python: >=3.6
License-File: LICENSE
